torch_nlm/__init__.py
torch_nlm/apply_2d_ops.py
torch_nlm/apply_3d_ops.py
torch_nlm/base_ops.py
nlm_torch-0.1.0.dist-info/LICENSE
nlm_torch-0.1.0.dist-info/METADATA
nlm_torch-0.1.0.dist-info/WHEEL
nlm_torch-0.1.0.dist-info/RECORD
