Metadata-Version: 2.1
Name: nlm-torch
Version: 0.1.0
Summary: PyTorch-based implementation of non-local means with GPU support.
License: LICENSE
Author: josegcpa
Author-email: jose.almeida@research.fchampalimaud.pt
Requires-Python: >=3.11,<4.0
Classifier: License :: Other/Proprietary License
Classifier: Programming Language :: Python :: 3
Classifier: Programming Language :: Python :: 3.11
Requires-Dist: Pillow (==10.0.0)
Requires-Dist: einops (==0.6.1)
Requires-Dist: numpy (==1.23.5)
Requires-Dist: torch (==2.0.1)
Requires-Dist: tqdm (==4.64.1)
